carota/__init__.py
carota/__main__.py
carota/carota.py
carota-1.1.0.dist-info/LICENSE
carota-1.1.0.dist-info/METADATA
carota-1.1.0.dist-info/WHEEL
carota-1.1.0.dist-info/entry_points.txt
carota-1.1.0.dist-info/top_level.txt
carota-1.1.0.dist-info/RECORD
