Metadata-Version: 2.1
Name: carota
Version: 1.1.0
Summary: Python random data CSV generator.
Home-page: https://github.com/fabiog1901/carota
Author: Fabio Ghirardello
Author-email: 
License: GPL v3.0
Keywords: csv generator
Platform: UNKNOWN
Classifier: License :: OSI Approved :: GNU General Public License v3 (GPLv3)
Classifier: Programming Language :: Python :: 3
Classifier: Programming Language :: Python :: 3.7
